easystockdata/__init__.py
easystockdata/indian.py
easystockdata/stock_apis.py
easystockdata/usa.py
easystockdata-0.1.10.dist-info/METADATA
easystockdata-0.1.10.dist-info/WHEEL
easystockdata-0.1.10.dist-info/RECORD
