Metadata-Version: 2.1
Name: easystockdata
Version: 0.1.10
Summary: A python module that gives stock price data and stock symbols.
Author: p_m_dhamecha
Author-email: pmdhamecha673@gmail.com
Requires-Python: >=3.9,<4.0
Classifier: Programming Language :: Python :: 3
Classifier: Programming Language :: Python :: 3.9
Classifier: Programming Language :: Python :: 3.10
Classifier: Programming Language :: Python :: 3.11
Classifier: Programming Language :: Python :: 3.12
Requires-Dist: requests (>=2.31.0,<3.0.0)
